django_spreadsheet/__init__.py
django_spreadsheet/_version.py
django_spreadsheet/django_spreadsheet.py
django_spreadsheet-1.4.0.dist-info/LICENSE
django_spreadsheet-1.4.0.dist-info/METADATA
django_spreadsheet-1.4.0.dist-info/WHEEL
django_spreadsheet-1.4.0.dist-info/top_level.txt
django_spreadsheet-1.4.0.dist-info/RECORD
