Metadata-Version: 2.1
Name: django-spreadsheet
Version: 1.4.0
Summary: Create a spreadsheet from the database with minimal code
Author-email: Antonis Christofides <antonis@antonischristofides.com>
Maintainer-email: Antonis Christofides <antonis@antonischristofides.com>
Project-URL: Homepage, https://github.com/aptiko/django-spreadsheet
Project-URL: Documentation, https://django-spreadsheet.readthedocs.io
Project-URL: Repository, https://github.com/aptiko/django-spreadsheet
Project-URL: Changelog, https://github.com/aptiko/django-spreadsheet/blob/master/CHANGELOG.rst
Keywords: django-spreadsheet
Classifier: Development Status :: 5 - Production/Stable
Classifier: Intended Audience :: Developers
Classifier: License :: OSI Approved :: BSD License
Classifier: Natural Language :: English
Classifier: Programming Language :: Python :: 3
Classifier: Programming Language :: Python :: 3.10
Classifier: Programming Language :: Python :: 3.11
Classifier: Programming Language :: Python :: 3.12
Classifier: Programming Language :: Python :: 3.13
Requires-Python: >=3.10
License-File: LICENSE
Requires-Dist: django<6,>=3.2
Requires-Dist: openpyxl<4,>=3
